{
  "annotations": {
    "list": [
      {
        "builtIn": 1,
        "datasource": {
          "type": "datasource",
          "uid": "grafana"
        },
        "enable": true,
        "hide": true,
        "iconColor": "rgba(0, 211, 255, 1)",
        "name": "Annotations & Alerts",
        "target": {
          "limit": 100,
          "matchAny": false,
          "tags": [],
          "type": "dashboard"
        },
        "type": "dashboard"
      }
    ]
  },
  "editable": true,
  "fiscalYearStartMonth": 0,
  "graphTooltip": 1,
  "iteration": 1669281032263,
  "links": [],
  "liveNow": false,
  "panels": [
    {
      "datasource": {
        "type": "prometheus",
        "uid": "P0D6E4079E36703EB"
      },
      "fieldConfig": {
        "defaults": {
          "decimals": 3,
          "mappings": [],
          "max": 100,
          "min": 0,
          "thresholds": {
            "mode": "absolute",
            "steps": [
              {
                "color": "rgb(0, 0, 0)",
                "value": null
              }
            ]
          },
          "unit": "percent"
        },
        "overrides": []
      },
      "gridPos": {
        "h": 3,
        "w": 4,
        "x": 0,
        "y": 0
      },
      "id": 4,
      "options": {
        "colorMode": "value",
        "graphMode": "none",
        "justifyMode": "center",
        "orientation": "auto",
        "reduceOptions": {
          "calcs": [
            "last"
          ],
          "fields": "",
          "values": false
        },
        "text": {},
        "textMode": "auto"
      },
      "pluginVersion": "8.5.13",
      "targets": [
        {
          "expr": "100 - kubernetes:error_slo:percent{service=\"$service\", location=\"$location\"}",
          "interval": "",
          "legendFormat": "{{ service }}",
          "refId": "A"
        }
      ],
      "title": "Availability Target",
      "type": "stat"
    },
    {
      "datasource": {
        "type": "prometheus",
        "uid": "P0D6E4079E36703EB"
      },
      "fieldConfig": {
        "defaults": {
          "mappings": [],
          "max": 1,
          "min": 0,
          "noValue": "No data",
          "thresholds": {
            "mode": "absolute",
            "steps": [
              {
                "color": "blue",
                "value": null
              }
            ]
          },
          "unit": "percentunit"
        },
        "overrides": []
      },
      "gridPos": {
        "h": 3,
        "w": 4,
        "x": 4,
        "y": 0
      },
      "id": 2,
      "options": {
        "colorMode": "value",
        "graphMode": "none",
        "justifyMode": "center",
        "orientation": "auto",
        "reduceOptions": {
          "calcs": [
            "last"
          ],
          "fields": "",
          "values": false
        },
        "text": {},
        "textMode": "auto"
      },
      "pluginVersion": "8.5.13",
      "targets": [
        {
          "expr": "1 - (kubernetes:service_location_namespace:errors_per_responses:ratio_rate[[span]]{service=\"$service\", location=\"$location\", namespace=\"$namespace\"}\nOR\nclamp_max(absent(kubernetes:service_location_namespace:errors_per_responses:ratio_rate[[span]]{service=\"$service\", location=\"$location\", namespace=\"$namespace\"}), 0)\n)",
          "interval": "",
          "legendFormat": "{{ service }}",
          "refId": "A"
        }
      ],
      "title": "Availability over $span",
      "type": "stat"
    },
    {
      "datasource": {
        "type": "prometheus",
        "uid": "P0D6E4079E36703EB"
      },
      "description": "",
      "fieldConfig": {
        "defaults": {
          "mappings": [
            {
              "options": {
                "0": {
                  "text": "Ok"
                },
                "1": {
                  "text": "Fail"
                }
              },
              "type": "value"
            }
          ],
          "thresholds": {
            "mode": "absolute",
            "steps": [
              {
                "color": "green",
                "value": null
              },
              {
                "color": "red",
                "value": 0.5
              }
            ]
          },
          "unit": "none"
        },
        "overrides": []
      },
      "gridPos": {
        "h": 3,
        "w": 4,
        "x": 8,
        "y": 0
      },
      "id": 5,
      "options": {
        "colorMode": "background",
        "graphMode": "none",
        "justifyMode": "center",
        "orientation": "auto",
        "reduceOptions": {
          "calcs": [
            "last"
          ],
          "fields": "",
          "values": false
        },
        "text": {},
        "textMode": "auto"
      },
      "pluginVersion": "8.5.13",
      "targets": [
        {
          "expr": "100 * (kubernetes:service_location_namespace:errors_per_responses:ratio_rate[[span]]{service=\"$service\", location=\"$location\", namespace=\"$namespace\"}\nOR\nclamp_max(absent(kubernetes:service_location_namespace:errors_per_responses:ratio_rate[[span]]{service=\"$service\", location=\"$location\", namespace=\"$namespace\"}), 0)\n)\n> bool on (service, location) kubernetes:error_slo:percent",
          "interval": "",
          "legendFormat": "{{ service }}",
          "refId": "A"
        }
      ],
      "title": "Availability Status over $span",
      "type": "stat"
    },
    {
      "datasource": {
        "type": "prometheus",
        "uid": "P0D6E4079E36703EB"
      },
      "description": "",
      "fieldConfig": {
        "defaults": {
          "mappings": [],
          "thresholds": {
            "mode": "absolute",
            "steps": [
              {
                "color": "rgb(0, 0, 0)",
                "value": null
              }
            ]
          },
          "unit": "s"
        },
        "overrides": []
      },
      "gridPos": {
        "h": 3,
        "w": 4,
        "x": 0,
        "y": 3
      },
      "id": 3,
      "options": {
        "colorMode": "value",
        "graphMode": "none",
        "justifyMode": "center",
        "orientation": "auto",
        "reduceOptions": {
          "calcs": [
            "last"
          ],
          "fields": "",
          "values": false
        },
        "text": {},
        "textMode": "auto"
      },
      "pluginVersion": "8.5.13",
      "targets": [
        {
          "expr": "kubernetes:latency_p99_slo:seconds{service=\"$service\", location=\"$location\"}",
          "interval": "",
          "legendFormat": "{{ service }}",
          "refId": "A"
        }
      ],
      "title": "P99 Latency Target",
      "type": "stat"
    },
    {
      "datasource": {
        "type": "prometheus",
        "uid": "P0D6E4079E36703EB"
      },
      "description": "",
      "fieldConfig": {
        "defaults": {
          "mappings": [],
          "thresholds": {
            "mode": "absolute",
            "steps": [
              {
                "color": "blue",
                "value": null
              }
            ]
          },
          "unit": "s"
        },
        "overrides": []
      },
      "gridPos": {
        "h": 3,
        "w": 4,
        "x": 4,
        "y": 3
      },
      "id": 6,
      "options": {
        "colorMode": "value",
        "graphMode": "none",
        "justifyMode": "center",
        "orientation": "auto",
        "reduceOptions": {
          "calcs": [
            "last"
          ],
          "fields": "",
          "values": false
        },
        "text": {},
        "textMode": "auto"
      },
      "pluginVersion": "8.5.13",
      "targets": [
        {
          "expr": "histogram_quantile (\n          0.99,\n          sum by (le, service, location, namespace)(\n            rate(ingress_nginx_detail_request_seconds_bucket{service=\"$service\", location=\"$location\", namespace=\"$namespace\"}[$span])\n          )\n        )",
          "interval": "",
          "legendFormat": "{{ service }}",
          "refId": "A"
        }
      ],
      "title": "P99 Latency over $span",
      "type": "stat"
    },
    {
      "datasource": {
        "type": "prometheus",
        "uid": "P0D6E4079E36703EB"
      },
      "description": "",
      "fieldConfig": {
        "defaults": {
          "mappings": [
            {
              "options": {
                "0": {
                  "text": "Ok"
                },
                "1": {
                  "text": "SLO Error"
                }
              },
              "type": "value"
            }
          ],
          "thresholds": {
            "mode": "absolute",
            "steps": [
              {
                "color": "green",
                "value": null
              },
              {
                "color": "red",
                "value": 0.5
              }
            ]
          },
          "unit": "none"
        },
        "overrides": []
      },
      "gridPos": {
        "h": 3,
        "w": 4,
        "x": 8,
        "y": 3
      },
      "id": 7,
      "options": {
        "colorMode": "background",
        "graphMode": "none",
        "justifyMode": "center",
        "orientation": "auto",
        "reduceOptions": {
          "calcs": [
            "last"
          ],
          "fields": "",
          "values": false
        },
        "text": {},
        "textMode": "auto"
      },
      "pluginVersion": "8.5.13",
      "targets": [
        {
          "expr": "histogram_quantile (\n          0.99,\n          sum by (le, service, location, namespace)(\n            rate(ingress_nginx_detail_request_seconds_bucket{service=\"$service\", location=\"$location\", namespace=\"$namespace\"}[$span])\n          )\n        )\n> bool on (service, location) kubernetes:latency_p99_slo:seconds",
          "interval": "",
          "legendFormat": "{{ service }}",
          "refId": "A"
        }
      ],
      "title": "P99 Latency Status",
      "type": "stat"
    },
    {
      "datasource": {
        "type": "prometheus",
        "uid": "P0D6E4079E36703EB"
      },
      "description": "",
      "fieldConfig": {
        "defaults": {
          "mappings": [],
          "thresholds": {
            "mode": "absolute",
            "steps": [
              {
                "color": "rgb(0, 0, 0)",
                "value": null
              }
            ]
          },
          "unit": "s"
        },
        "overrides": []
      },
      "gridPos": {
        "h": 3,
        "w": 4,
        "x": 0,
        "y": 6
      },
      "id": 14,
      "options": {
        "colorMode": "value",
        "graphMode": "none",
        "justifyMode": "center",
        "orientation": "auto",
        "reduceOptions": {
          "calcs": [
            "last"
          ],
          "fields": "",
          "values": false
        },
        "text": {},
        "textMode": "auto"
      },
      "pluginVersion": "8.5.13",
      "targets": [
        {
          "expr": "kubernetes:latency_p90_slo:seconds{service=\"$service\", location=\"$location\"}",
          "interval": "",
          "legendFormat": "{{ service }}",
          "refId": "A"
        }
      ],
      "title": "P90 Latency Target",
      "type": "stat"
    },
    {
      "datasource": {
        "type": "prometheus",
        "uid": "P0D6E4079E36703EB"
      },
      "description": "",
      "fieldConfig": {
        "defaults": {
          "mappings": [],
          "thresholds": {
            "mode": "absolute",
            "steps": [
              {
                "color": "blue",
                "value": null
              }
            ]
          },
          "unit": "s"
        },
        "overrides": []
      },
      "gridPos": {
        "h": 3,
        "w": 4,
        "x": 4,
        "y": 6
      },
      "id": 15,
      "options": {
        "colorMode": "value",
        "graphMode": "none",
        "justifyMode": "center",
        "orientation": "auto",
        "reduceOptions": {
          "calcs": [
            "last"
          ],
          "fields": "",
          "values": false
        },
        "text": {},
        "textMode": "auto"
      },
      "pluginVersion": "8.5.13",
      "targets": [
        {
          "expr": "histogram_quantile (\n          0.90,\n          sum by (le, service, location, namespace)(\n            rate(ingress_nginx_detail_request_seconds_bucket{service=\"$service\", location=\"$location\", namespace=\"$namespace\"}[$span])\n          )\n        )",
          "interval": "",
          "legendFormat": "{{ service }}",
          "refId": "A"
        }
      ],
      "title": "P90 Latency over $span",
      "type": "stat"
    },
    {
      "datasource": {
        "type": "prometheus",
        "uid": "P0D6E4079E36703EB"
      },
      "description": "",
      "fieldConfig": {
        "defaults": {
          "mappings": [
            {
              "options": {
                "0": {
                  "text": "Ok"
                },
                "1": {
                  "text": "SLO Error"
                }
              },
              "type": "value"
            }
          ],
          "thresholds": {
            "mode": "absolute",
            "steps": [
              {
                "color": "green",
                "value": null
              },
              {
                "color": "red",
                "value": 0.5
              }
            ]
          },
          "unit": "none"
        },
        "overrides": []
      },
      "gridPos": {
        "h": 3,
        "w": 4,
        "x": 8,
        "y": 6
      },
      "id": 16,
      "options": {
        "colorMode": "background",
        "graphMode": "none",
        "justifyMode": "center",
        "orientation": "auto",
        "reduceOptions": {
          "calcs": [
            "last"
          ],
          "fields": "",
          "values": false
        },
        "text": {},
        "textMode": "auto"
      },
      "pluginVersion": "8.5.13",
      "targets": [
        {
          "expr": "histogram_quantile (\n          0.90,\n          sum by (le, service, location, namespace)(\n            rate(ingress_nginx_detail_request_seconds_bucket{service=\"$service\", location=\"$location\", namespace=\"$namespace\"}[$span])\n          )\n        )\n> bool on (service, location) kubernetes:latency_p90_slo:seconds",
          "interval": "",
          "legendFormat": "{{ service }}",
          "refId": "A"
        }
      ],
      "title": "P90 Latency Status",
      "type": "stat"
    },
    {
      "datasource": {
        "type": "prometheus",
        "uid": "P0D6E4079E36703EB"
      },
      "description": "",
      "fieldConfig": {
        "defaults": {
          "color": {
            "mode": "palette-classic"
          },
          "custom": {
            "axisLabel": "",
            "axisPlacement": "auto",
            "barAlignment": 0,
            "drawStyle": "line",
            "fillOpacity": 10,
            "gradientMode": "none",
            "hideFrom": {
              "legend": false,
              "tooltip": false,
              "viz": false
            },
            "lineInterpolation": "linear",
            "lineWidth": 1,
            "pointSize": 5,
            "scaleDistribution": {
              "type": "linear"
            },
            "showPoints": "never",
            "spanNulls": false,
            "stacking": {
              "group": "A",
              "mode": "none"
            },
            "thresholdsStyle": {
              "mode": "line+area"
            }
          },
          "links": [],
          "mappings": [],
          "min": 0,
          "thresholds": {
            "mode": "absolute",
            "steps": [
              {
                "color": "transparent",
                "value": null
              },
              {
                "color": "red",
                "value": 0.001
              }
            ]
          },
          "unit": "percentunit"
        },
        "overrides": []
      },
      "gridPos": {
        "h": 7,
        "w": 24,
        "x": 0,
        "y": 9
      },
      "id": 9,
      "options": {
        "legend": {
          "calcs": [],
          "displayMode": "hidden",
          "placement": "bottom"
        },
        "tooltip": {
          "mode": "multi",
          "sort": "none"
        }
      },
      "pluginVersion": "8.5.13",
      "targets": [
        {
          "expr": "kubernetes:service_location_namespace:errors_per_responses:ratio_rate5m{service=\"$service\", location=\"$location\", namespace=\"$namespace\"}",
          "interval": "",
          "legendFormat": "",
          "refId": "A"
        }
      ],
      "title": "Errors ratio over 5m (location: $location)",
      "type": "timeseries"
    },
    {
      "datasource": {
        "type": "prometheus",
        "uid": "P0D6E4079E36703EB"
      },
      "description": "",
      "fieldConfig": {
        "defaults": {
          "color": {
            "mode": "palette-classic"
          },
          "custom": {
            "axisLabel": "",
            "axisPlacement": "auto",
            "barAlignment": 0,
            "drawStyle": "line",
            "fillOpacity": 10,
            "gradientMode": "none",
            "hideFrom": {
              "legend": false,
              "tooltip": false,
              "viz": false
            },
            "lineInterpolation": "linear",
            "lineWidth": 1,
            "pointSize": 5,
            "scaleDistribution": {
              "type": "linear"
            },
            "showPoints": "never",
            "spanNulls": false,
            "stacking": {
              "group": "A",
              "mode": "none"
            },
            "thresholdsStyle": {
              "mode": "off"
            }
          },
          "links": [],
          "mappings": [],
          "min": 0,
          "thresholds": {
            "mode": "absolute",
            "steps": [
              {
                "color": "green",
                "value": null
              },
              {
                "color": "red",
                "value": 80
              }
            ]
          },
          "unit": "s"
        },
        "overrides": []
      },
      "gridPos": {
        "h": 7,
        "w": 24,
        "x": 0,
        "y": 16
      },
      "id": 13,
      "options": {
        "legend": {
          "calcs": [],
          "displayMode": "list",
          "placement": "bottom"
        },
        "tooltip": {
          "mode": "multi",
          "sort": "none"
        }
      },
      "pluginVersion": "8.5.13",
      "targets": [
        {
          "expr": "kubernetes:service_location_namespace:request_latency_seconds:p90_rate5m{service=\"$service\", location=\"$location\", namespace=\"$namespace\"}",
          "interval": "",
          "legendFormat": "90th percentile",
          "refId": "A"
        },
        {
          "expr": "kubernetes:service_location_namespace:request_latency_seconds:p99_rate5m{service=\"$service\", location=\"$location\", namespace=\"$namespace\"}",
          "interval": "",
          "legendFormat": "99th percentile",
          "refId": "B"
        }
      ],
      "title": "Latency over 5m (location: $location)",
      "type": "timeseries"
    },
    {
      "datasource": {
        "type": "prometheus",
        "uid": "P0D6E4079E36703EB"
      },
      "description": "",
      "fieldConfig": {
        "defaults": {
          "color": {
            "mode": "palette-classic"
          },
          "custom": {
            "axisLabel": "",
            "axisPlacement": "auto",
            "barAlignment": 0,
            "drawStyle": "line",
            "fillOpacity": 10,
            "gradientMode": "none",
            "hideFrom": {
              "legend": false,
              "tooltip": false,
              "viz": false
            },
            "lineInterpolation": "linear",
            "lineWidth": 1,
            "pointSize": 5,
            "scaleDistribution": {
              "type": "linear"
            },
            "showPoints": "never",
            "spanNulls": false,
            "stacking": {
              "group": "A",
              "mode": "none"
            },
            "thresholdsStyle": {
              "mode": "off"
            }
          },
          "links": [],
          "mappings": [],
          "min": 0,
          "thresholds": {
            "mode": "absolute",
            "steps": [
              {
                "color": "green",
                "value": null
              },
              {
                "color": "red",
                "value": 80
              }
            ]
          },
          "unit": "short"
        },
        "overrides": []
      },
      "gridPos": {
        "h": 7,
        "w": 24,
        "x": 0,
        "y": 23
      },
      "id": 11,
      "options": {
        "legend": {
          "calcs": [],
          "displayMode": "list",
          "placement": "bottom"
        },
        "tooltip": {
          "mode": "multi",
          "sort": "none"
        }
      },
      "pluginVersion": "8.5.13",
      "targets": [
        {
          "datasource": {
            "type": "prometheus",
            "uid": "P0D6E4079E36703EB"
          },
          "editorMode": "code",
          "expr": "sum by (location, method)(rate(ingress_nginx_detail_requests_total{job=\"nginx-ingress-controller\", service=\"$service\", namespace=\"$namespace\"}[$__rate_interval]))",
          "interval": "",
          "legendFormat": "{{ method }} {{ location }}",
          "range": true,
          "refId": "A"
        }
      ],
      "title": "Avg RPS by location",
      "type": "timeseries"
    }
  ],
  "schemaVersion": 36,
  "style": "dark",
  "tags": [],
  "templating": {
    "list": [
      {
        "current": {
          "selected": false,
          "text": "30m",
          "value": "30m"
        },
        "hide": 0,
        "includeAll": false,
        "multi": false,
        "name": "span",
        "options": [
          {
            "selected": false,
            "text": "5m",
            "value": "5m"
          },
          {
            "selected": true,
            "text": "30m",
            "value": "30m"
          },
          {
            "selected": false,
            "text": "1h",
            "value": "1h"
          },
          {
            "selected": false,
            "text": "2h",
            "value": "2h"
          },
          {
            "selected": false,
            "text": "6h",
            "value": "6h"
          },
          {
            "selected": false,
            "text": "1d",
            "value": "1d"
          },
          {
            "selected": false,
            "text": "3d",
            "value": "3d"
          }
        ],
        "query": "5m, 30m, 1h, 2h, 6h, 1d, 3d",
        "queryValue": "",
        "skipUrlSync": false,
        "type": "custom"
      },
      {
        "current": {
          "selected": false,
          "text": "prod",
          "value": "prod"
        },
        "datasource": {
          "type": "prometheus",
          "uid": "P0D6E4079E36703EB"
        },
        "definition": "label_values(ingress_nginx_detail_responses_total{job=\"nginx-ingress-controller\", namespace=~\"(test|stage|prod)\"}, namespace) ",
        "hide": 0,
        "includeAll": false,
        "multi": false,
        "name": "namespace",
        "options": [],
        "query": {
          "query": "label_values(ingress_nginx_detail_responses_total{job=\"nginx-ingress-controller\", namespace=~\"(test|stage|prod)\"}, namespace) ",
          "refId": "StandardVariableQuery"
        },
        "refresh": 1,
        "regex": "",
        "skipUrlSync": false,
        "sort": 0,
        "tagValuesQuery": "",
        "tagsQuery": "",
        "type": "query",
        "useTags": false
      },
      {
        "current": {
          "selected": false,
          "text": "logistic-calculator",
          "value": "logistic-calculator"
        },
        "datasource": {
          "type": "prometheus",
          "uid": "P0D6E4079E36703EB"
        },
        "definition": "label_values(ingress_nginx_detail_responses_total{job=\"nginx-ingress-controller\", namespace=\"$namespace\"}, service) ",
        "hide": 0,
        "includeAll": false,
        "multi": false,
        "name": "service",
        "options": [],
        "query": {
          "query": "label_values(ingress_nginx_detail_responses_total{job=\"nginx-ingress-controller\", namespace=\"$namespace\"}, service) ",
          "refId": "main-service-Variable-Query"
        },
        "refresh": 1,
        "regex": "",
        "skipUrlSync": false,
        "sort": 0,
        "tagValuesQuery": "",
        "tagsQuery": "",
        "type": "query",
        "useTags": false
      },
      {
        "current": {
          "selected": false,
          "text": "/v1/deliveryestimates:min",
          "value": "/v1/deliveryestimates:min"
        },
        "datasource": {
          "type": "prometheus",
          "uid": "P0D6E4079E36703EB"
        },
        "definition": "label_values(ingress_nginx_detail_responses_total{job=\"nginx-ingress-controller\", namespace=\"$namespace\", service=\"$service\"}, location) ",
        "hide": 0,
        "includeAll": false,
        "multi": false,
        "name": "location",
        "options": [],
        "query": {
          "query": "label_values(ingress_nginx_detail_responses_total{job=\"nginx-ingress-controller\", namespace=\"$namespace\", service=\"$service\"}, location) ",
          "refId": "main-location-Variable-Query"
        },
        "refresh": 2,
        "regex": "",
        "skipUrlSync": false,
        "sort": 0,
        "tagValuesQuery": "",
        "tagsQuery": "",
        "type": "query",
        "useTags": false
      }
    ]
  },
  "time": {
    "from": "now-1h",
    "to": "now"
  },
  "timepicker": {
    "refresh_intervals": [
      "10s",
      "30s",
      "1m",
      "5m",
      "15m",
      "30m",
      "1h",
      "2h",
      "1d"
    ]
  },
  "timezone": "browser",
  "title": "SLOs: Availability and Latency",
  "uid": "Wh4rOM3Mk",
  "version": 1,
  "weekStart": ""
}